[
  {
    "osm_id": 967790408,
    "osm_type": "node",
    "name": "Brasserie Grand-Café De Smaeckkamer",
    "amenity": "restaurant",
    "lat": 52.4838314,
    "lng": 4.6436225,
    "address": "Westerhoutplein 6",
    "city": "Beverwijk",
    "website": "https://www.desmaeckkamer.nl/",
    "phone": "+31 251 296 220",
    "cuisine": null,
    "outdoor_seating": null,
    "wheelchair": null,
    "opening_hours": "Tu-Su 08:00-24:00",
    "scrape": {
      "success": true,
      "keywords": [
        "speeltuin",
        "kinderen",
        "kinderkaart"
      ],
      "snippet": "ark westerhout aanschuiven voor een kop heerlijke bocca koffie met huisgemaakt gebak of een lekker ontbijt? met de hele familie lunchen op het terras of in de brasserie terwijl de kinderen zich in de speeltuin of kinderkamer vermaken? een gezellig diner met een goed glas wijn samen met je beste vrienden? het kan bij de smaeckkamer allemaal. maar ook een romantische bruiloft grenzend aan park westerhout, een swingende feestavond, een walking diner op ons zonovergoten terras of een high tea met vr",
      "textLength": 1848
    },
    "evaluation": {
      "score": 8,
      "confidence": "high",
      "reasoning": "Expliciet kindvriendelijk met speeltuin, kinderkamer en kinderkaart genoemd.",
      "has_play_area": true,
      "has_high_chairs": null,
      "has_kids_menu": true,
      "has_diaper_changing": null,
      "weather": "both",
      "description": "Brasserie Grand-Café De Smaeckkamer biedt een speeltuin en kinderkamer waar peuters zich kunnen vermaken terwijl ouders genieten van eten en drinken.",
      "toddler_highlight": "Speeltuin en kinderkamer beschikbaar, ideaal voor peuters.",
      "is_pancake_restaurant": false
    }
  },
  {
    "osm_id": 995967626,
    "osm_type": "node",
    "name": "Grand Café Cineac",
    "amenity": "restaurant",
    "lat": 52.4777915,
    "lng": 4.6534402,
    "address": "Stationsplein 49",
    "city": "Beverwijk",
    "website": "https://grandcafecineac.nl/",
    "phone": "+31 251 272 474",
    "cuisine": null,
    "outdoor_seating": null,
    "wheelchair": "yes",
    "opening_hours": "Mo-Fr 11:00-24:00; Sa-Su 12:00-24:00",
    "scrape": {
      "success": true,
      "keywords": [],
      "snippet": null,
      "textLength": 1618
    },
    "evaluation": {
      "score": 4,
      "confidence": "low",
      "reasoning": "Geen website-aanwijzingen gevonden voor kindvriendelijkheid.",
      "has_play_area": null,
      "has_high_chairs": null,
      "has_kids_menu": null,
      "has_diaper_changing": null,
      "weather": null,
      "description": null,
      "toddler_highlight": null,
      "is_pancake_restaurant": false
    }
  },
  {
    "osm_id": 2903930769,
    "osm_type": "node",
    "name": "Be my Guest",
    "amenity": "restaurant",
    "lat": 52.492313,
    "lng": 4.5915682,
    "address": "Voorstraat 4",
    "city": "Wijk aan Zee",
    "website": "https://www.bemyguest.house",
    "phone": "+31 251 295 326",
    "cuisine": "international",
    "outdoor_seating": null,
    "wheelchair": "yes",
    "opening_hours": "Mo-We,Fr 15:00-22:00; Sa-Su 09:00-22:00; PH closed",
    "scrape": {
      "success": true,
      "keywords": [],
      "snippet": null,
      "textLength": 8548
    },
    "evaluation": {
      "score": 4,
      "confidence": "low",
      "reasoning": "Geen website-aanwijzingen gevonden voor kindvriendelijkheid.",
      "has_play_area": null,
      "has_high_chairs": null,
      "has_kids_menu": null,
      "has_diaper_changing": null,
      "weather": null,
      "description": null,
      "toddler_highlight": null,
      "is_pancake_restaurant": false
    }
  },
  {
    "osm_id": 2903930771,
    "osm_type": "node",
    "name": "De Liefhebbers aan Zee",
    "amenity": "restaurant",
    "lat": 52.4951594,
    "lng": 4.5877054,
    "address": "Zeepad 4",
    "city": "Wijk aan Zee",
    "website": "https://de-liefhebbers.nl/",
    "phone": null,
    "cuisine": "lunch;diner",
    "outdoor_seating": null,
    "wheelchair": null,
    "opening_hours": null,
    "scrape": {
      "success": true,
      "keywords": [],
      "snippet": null,
      "textLength": 1425
    },
    "evaluation": {
      "score": 4,
      "confidence": "low",
      "reasoning": "Geen website-aanwijzingen gevonden voor kindvriendelijkheid.",
      "has_play_area": null,
      "has_high_chairs": null,
      "has_kids_menu": null,
      "has_diaper_changing": null,
      "weather": null,
      "description": null,
      "toddler_highlight": null,
      "is_pancake_restaurant": false
    }
  },
  {
    "osm_id": 2903931218,
    "osm_type": "node",
    "name": "Restaurant Tarantella",
    "amenity": "restaurant",
    "lat": 52.4942781,
    "lng": 4.5943329,
    "address": "Relweg 5",
    "city": "Wijk aan Zee",
    "website": "http://www.restaurant-tarantella.nl",
    "phone": "+31 251 375 350",
    "cuisine": "pizza",
    "outdoor_seating": null,
    "wheelchair": null,
    "opening_hours": "Mo-Su 17:00-22:00",
    "scrape": {
      "success": false,
      "error": "This operation was aborted"
    },
    "evaluation": {
      "score": 4,
      "confidence": "low",
      "reasoning": "Geen website-aanwijzingen gevonden voor kindvriendelijkheid.",
      "has_play_area": null,
      "has_high_chairs": null,
      "has_kids_menu": null,
      "has_diaper_changing": null,
      "weather": null,
      "description": null,
      "toddler_highlight": null,
      "is_pancake_restaurant": false
    }
  },
  {
    "osm_id": 2903931808,
    "osm_type": "node",
    "name": "Het Strandhuis",
    "amenity": "restaurant",
    "lat": 52.4936409,
    "lng": 4.5849935,
    "address": "Strand Zuiderbad 75",
    "city": "Wijk aan Zee",
    "website": "https://www.het-strandhuis.nl",
    "phone": null,
    "cuisine": null,
    "outdoor_seating": null,
    "wheelchair": "yes",
    "opening_hours": null,
    "scrape": {
      "success": false,
      "error": "fetch failed"
    },
    "evaluation": {
      "score": 4,
      "confidence": "low",
      "reasoning": "Geen website-aanwijzingen gevonden voor kindvriendelijkheid.",
      "has_play_area": null,
      "has_high_chairs": null,
      "has_kids_menu": null,
      "has_diaper_changing": null,
      "weather": null,
      "description": null,
      "toddler_highlight": null,
      "is_pancake_restaurant": false
    }
  },
  {
    "osm_id": 2909587275,
    "osm_type": "node",
    "name": "De Beren",
    "amenity": "restaurant",
    "lat": 52.4959221,
    "lng": 4.6653103,
    "address": "Wijkerbaan 24",
    "city": "Beverwijk",
    "website": "https://www.beren.nl/vestigingen/beverwijk-wijkerbaan",
    "phone": "+31 251 343 013",
    "cuisine": "burger;chicken;grill",
    "outdoor_seating": null,
    "wheelchair": null,
    "opening_hours": null,
    "scrape": {
      "success": true,
      "keywords": [],
      "snippet": null,
      "textLength": 3205
    },
    "evaluation": {
      "score": 4,
      "confidence": "low",
      "reasoning": "Geen website-aanwijzingen gevonden voor kindvriendelijkheid.",
      "has_play_area": null,
      "has_high_chairs": null,
      "has_kids_menu": null,
      "has_diaper_changing": null,
      "weather": null,
      "description": null,
      "toddler_highlight": null,
      "is_pancake_restaurant": false
    }
  },
  {
    "osm_id": 2909595684,
    "osm_type": "node",
    "name": "Gasthoeve Adrichem",
    "amenity": "restaurant",
    "lat": 52.4880862,
    "lng": 4.6707096,
    "address": "Adrichemlaan 5",
    "city": "Beverwijk",
    "website": "https://www.gasthoeveadrichem.nl/",
    "phone": "+31 251 254 333",
    "cuisine": null,
    "outdoor_seating": null,
    "wheelchair": null,
    "opening_hours": "We-Su 17:00-21:00",
    "scrape": {
      "success": true,
      "keywords": [],
      "snippet": null,
      "textLength": 1156
    },
    "evaluation": {
      "score": 4,
      "confidence": "low",
      "reasoning": "Geen website-aanwijzingen gevonden voor kindvriendelijkheid.",
      "has_play_area": null,
      "has_high_chairs": null,
      "has_kids_menu": null,
      "has_diaper_changing": null,
      "weather": null,
      "description": null,
      "toddler_highlight": null,
      "is_pancake_restaurant": false
    }
  },
  {
    "osm_id": 2911206280,
    "osm_type": "node",
    "name": "Pasta Vino",
    "amenity": "restaurant",
    "lat": 52.4822899,
    "lng": 4.6572763,
    "address": "Begijnenstraat 11",
    "city": "Beverwijk",
    "website": "https://www.pasta-vino.nl/",
    "phone": null,
    "cuisine": "italian",
    "outdoor_seating": null,
    "wheelchair": null,
    "opening_hours": null,
    "scrape": {
      "success": false,
      "error": "fetch failed"
    },
    "evaluation": {
      "score": 4,
      "confidence": "low",
      "reasoning": "Geen website-aanwijzingen gevonden voor kindvriendelijkheid.",
      "has_play_area": null,
      "has_high_chairs": null,
      "has_kids_menu": null,
      "has_diaper_changing": null,
      "weather": null,
      "description": null,
      "toddler_highlight": null,
      "is_pancake_restaurant": false
    }
  },
  {
    "osm_id": 2911215756,
    "osm_type": "node",
    "name": "Mes's Burger Factory",
    "amenity": "restaurant",
    "lat": 52.4834773,
    "lng": 4.6606559,
    "address": "Breestraat 161",
    "city": "Beverwijk",
    "website": "http://www.messburgerfactory.nl/",
    "phone": null,
    "cuisine": null,
    "outdoor_seating": null,
    "wheelchair": null,
    "opening_hours": null,
    "scrape": {
      "success": true,
      "keywords": [],
      "snippet": null,
      "textLength": 74
    },
    "evaluation": {
      "score": 4,
      "confidence": "low",
      "reasoning": "Geen website-aanwijzingen gevonden voor kindvriendelijkheid.",
      "has_play_area": null,
      "has_high_chairs": null,
      "has_kids_menu": null,
      "has_diaper_changing": null,
      "weather": null,
      "description": null,
      "toddler_highlight": null,
      "is_pancake_restaurant": false
    }
  },
  {
    "osm_id": 2911215773,
    "osm_type": "node",
    "name": "Pop Chicken",
    "amenity": "fast_food",
    "lat": 52.4835619,
    "lng": 4.6608044,
    "address": "Breestraat 163",
    "city": "Beverwijk",
    "website": "https://www.popchickenbeverwijk.nl/",
    "phone": null,
    "cuisine": null,
    "outdoor_seating": null,
    "wheelchair": null,
    "opening_hours": null,
    "scrape": {
      "success": false,
      "error": "fetch failed"
    },
    "evaluation": {
      "score": 4,
      "confidence": "low",
      "reasoning": "Geen website-aanwijzingen gevonden voor kindvriendelijkheid.",
      "has_play_area": null,
      "has_high_chairs": null,
      "has_kids_menu": null,
      "has_diaper_changing": null,
      "weather": null,
      "description": null,
      "toddler_highlight": null,
      "is_pancake_restaurant": false
    }
  },
  {
    "osm_id": 2911215791,
    "osm_type": "node",
    "name": "Steakhouse Pizzeria Beverwijk",
    "amenity": "restaurant",
    "lat": 52.4836106,
    "lng": 4.6608844,
    "address": "Breestraat 165",
    "city": "Beverwijk",
    "website": "https://www.thuisbezorgd.nl/steakhouse-pizzeria",
    "phone": null,
    "cuisine": null,
    "outdoor_seating": null,
    "wheelchair": null,
    "opening_hours": null,
    "scrape": {
      "success": false,
      "error": "HTTP 403"
    },
    "evaluation": {
      "score": 4,
      "confidence": "low",
      "reasoning": "Geen website-aanwijzingen gevonden voor kindvriendelijkheid.",
      "has_play_area": null,
      "has_high_chairs": null,
      "has_kids_menu": null,
      "has_diaper_changing": null,
      "weather": null,
      "description": null,
      "toddler_highlight": null,
      "is_pancake_restaurant": false
    }
  },
  {
    "osm_id": 2911219950,
    "osm_type": "node",
    "name": "WOKKI",
    "amenity": "fast_food",
    "lat": 52.4811213,
    "lng": 4.654615,
    "address": "Zeestraat 19",
    "city": "Beverwijk",
    "website": "https://www.bestelwokki.nl/",
    "phone": null,
    "cuisine": null,
    "outdoor_seating": null,
    "wheelchair": null,
    "opening_hours": null,
    "scrape": {
      "success": true,
      "keywords": [],
      "snippet": null,
      "textLength": 17321
    },
    "evaluation": {
      "score": 4,
      "confidence": "low",
      "reasoning": "Geen website-aanwijzingen gevonden voor kindvriendelijkheid.",
      "has_play_area": null,
      "has_high_chairs": null,
      "has_kids_menu": null,
      "has_diaper_changing": null,
      "weather": null,
      "description": null,
      "toddler_highlight": null,
      "is_pancake_restaurant": false
    }
  },
  {
    "osm_id": 2911243604,
    "osm_type": "node",
    "name": "FEBO",
    "amenity": "fast_food",
    "lat": 52.4830966,
    "lng": 4.6601322,
    "address": "Beverhof 45",
    "city": "Beverwijk",
    "website": "https://www.febo-beverwijk.nl/",
    "phone": null,
    "cuisine": "friture",
    "outdoor_seating": null,
    "wheelchair": "yes",
    "opening_hours": null,
    "scrape": {
      "success": false,
      "error": "fetch failed"
    },
    "evaluation": {
      "score": 4,
      "confidence": "low",
      "reasoning": "Geen website-aanwijzingen gevonden voor kindvriendelijkheid.",
      "has_play_area": null,
      "has_high_chairs": null,
      "has_kids_menu": null,
      "has_diaper_changing": null,
      "weather": null,
      "description": null,
      "toddler_highlight": null,
      "is_pancake_restaurant": false
    }
  },
  {
    "osm_id": 2911244129,
    "osm_type": "node",
    "name": "Chiangmai",
    "amenity": "restaurant",
    "lat": 52.4817415,
    "lng": 4.6531621,
    "address": "Zeestraat 46",
    "city": "Beverwijk",
    "website": "https://www.thai-restaurant-chiangmai.nl/",
    "phone": "+31 251 227 979",
    "cuisine": "thai",
    "outdoor_seating": null,
    "wheelchair": null,
    "opening_hours": "16:00-22:00",
    "scrape": {
      "success": true,
      "keywords": [],
      "snippet": null,
      "textLength": 14439
    },
    "evaluation": {
      "score": 4,
      "confidence": "low",
      "reasoning": "Geen website-aanwijzingen gevonden voor kindvriendelijkheid.",
      "has_play_area": null,
      "has_high_chairs": null,
      "has_kids_menu": null,
      "has_diaper_changing": null,
      "weather": null,
      "description": null,
      "toddler_highlight": null,
      "is_pancake_restaurant": false
    }
  },
  {
    "osm_id": 2911254699,
    "osm_type": "node",
    "name": "La Cubanita",
    "amenity": "restaurant",
    "lat": 52.4781596,
    "lng": 4.65094,
    "address": "Velserweg 8",
    "city": "Beverwijk",
    "website": "https://lacubanita.nl/tapas-beverwijk",
    "phone": "+31 251 769104",
    "cuisine": "tapas",
    "outdoor_seating": null,
    "wheelchair": "yes",
    "opening_hours": null,
    "scrape": {
      "success": true,
      "keywords": [],
      "snippet": null,
      "textLength": 1756
    },
    "evaluation": {
      "score": 4,
      "confidence": "low",
      "reasoning": "Geen website-aanwijzingen gevonden voor kindvriendelijkheid.",
      "has_play_area": null,
      "has_high_chairs": null,
      "has_kids_menu": null,
      "has_diaper_changing": null,
      "weather": null,
      "description": null,
      "toddler_highlight": null,
      "is_pancake_restaurant": false
    }
  },
  {
    "osm_id": 4403276523,
    "osm_type": "node",
    "name": "Wereldrestaurant Beverhof",
    "amenity": "restaurant",
    "lat": 52.4829898,
    "lng": 4.6601276,
    "address": "Beverhof 44",
    "city": "Beverwijk",
    "website": "https://wereldrestaurantbeverhof.nl/",
    "phone": null,
    "cuisine": null,
    "outdoor_seating": null,
    "wheelchair": "yes",
    "opening_hours": null,
    "scrape": {
      "success": true,
      "keywords": [
        "speelhoek",
        "kinderen",
        "kindvriendelijk"
      ],
      "snippet": "eugde met uw dierbaren. ons restaurant is ontworpen om een warme en uitnodigende sfeer te creëren, waar elke maaltijd een bijzondere ervaring wordt. van het kindvriendelijke buffet tot onze gezellige speelhoek, wij zorgen ervoor dat ook de jongste gasten een onvergetelijke tijd beleven. verken de wereld van culinaire wonderen bij wereldrestaurant beverhof. reserveer uw tafel vandaag nog en maak u klaar voor een culinaire reis die u niet snel zult vergeten. reserveer online prijzen bij wereldrest",
      "textLength": 9649
    },
    "evaluation": {
      "score": 8,
      "confidence": "high",
      "reasoning": "Expliciet kindvriendelijk buffet en gezellige speelhoek voor jonge gasten.",
      "has_play_area": true,
      "has_high_chairs": null,
      "has_kids_menu": true,
      "has_diaper_changing": null,
      "weather": "indoor",
      "description": "Wereldrestaurant Beverhof is ontworpen als kindvriendelijke plek met speelhoek en kindvriendelijk buffet waar peuters welkom zijn.",
      "toddler_highlight": "Gezellige speelhoek en kindvriendelijk buffet voor peuters.",
      "is_pancake_restaurant": false
    }
  },
  {
    "osm_id": 4403276525,
    "osm_type": "node",
    "name": "Döner Delight",
    "amenity": "fast_food",
    "lat": 52.4830897,
    "lng": 4.6604709,
    "address": "Beverhof 46",
    "city": "Beverwijk",
    "website": "https://www.doner-delight-beverwijk-beverwijk.nl/",
    "phone": null,
    "cuisine": null,
    "outdoor_seating": null,
    "wheelchair": null,
    "opening_hours": null,
    "scrape": {
      "success": true,
      "keywords": [
        "kinderen",
        "kindermenu"
      ],
      "snippet": "€ 0,00), € 10,61/l, 0,33l red bull energy drink 250ml stimuleert lichaam en geest. red bull energy drink wordt wereldwijd gewaardeerd door topsporters € 3,75 hoog cafeïnegehalte. niet aanbevolen voor kinderen en zwangere vrouwen of vrouwen die borstvoeding geven (32,0 mg/100 ml), incl. statiegeld (€ 0,00), € 15,00/l, 0,25l fuze tea green tea 330ml € 2,75 incl. statiegeld (€ 0,00) fuze tea peach hibiscus 330ml € 2,75 incl. statiegeld (€ 0,00) chocomel 250ml € 3,75 incl. statiegeld (€ 0,00), € 15,",
      "textLength": 8181
    },
    "evaluation": {
      "score": 4,
      "confidence": "medium",
      "reasoning": "Kindermenu aanwezig maar beperkte informatie; fast-food concept zonder duidelijke peuter-voorzieningen.",
      "has_play_area": false,
      "has_high_chairs": null,
      "has_kids_menu": true,
      "has_diaper_changing": null,
      "weather": "indoor",
      "description": null,
      "toddler_highlight": null,
      "is_pancake_restaurant": false
    }
  },
  {
    "osm_id": 5435415488,
    "osm_type": "node",
    "name": "McDonald's",
    "amenity": "fast_food",
    "lat": 52.4801519,
    "lng": 4.6658109,
    "address": "Parallelweg 122",
    "city": "Beverwijk",
    "website": "https://www.mcdonalds.com/nl/nl-nl/location/beverwijk/mcdonalds-beverwijk/parallelweg-122/850081.html",
    "phone": "+31 251 227 072",
    "cuisine": "burger",
    "outdoor_seating": null,
    "wheelchair": "yes",
    "opening_hours": "09:00-22:00 open \"Restaurant\" || 08:00-01:00 open \"McDrive\"",
    "scrape": {
      "success": true,
      "keywords": [],
      "snippet": null,
      "textLength": 2757
    },
    "evaluation": {
      "score": 4,
      "confidence": "low",
      "reasoning": "Geen website-aanwijzingen gevonden voor kindvriendelijkheid.",
      "has_play_area": null,
      "has_high_chairs": null,
      "has_kids_menu": null,
      "has_diaper_changing": null,
      "weather": null,
      "description": null,
      "toddler_highlight": null,
      "is_pancake_restaurant": false
    }
  },
  {
    "osm_id": 11231270214,
    "osm_type": "node",
    "name": "Paviljoen de Kust",
    "amenity": "restaurant",
    "lat": 52.49783,
    "lng": 4.5869689,
    "address": "strand Noorderbad 20 20",
    "city": "Wijk aan Zee",
    "website": "https://www.roompot.nl/strandpaviljoen-de-kust/",
    "phone": null,
    "cuisine": "breakfast;diner;lunch",
    "outdoor_seating": null,
    "wheelchair": null,
    "opening_hours": null,
    "scrape": {
      "success": true,
      "keywords": [
        "kindvriendelijk"
      ],
      "snippet": "l certificaat veilige gegevensoverdracht veilige betaling vakantieparken vakantieparken nederland vakantieparken belgi&#235; vakantieparken duitsland type vakantie huisdiervriendelijke vakantieparken kindvriendelijke vakantieparken luxe vakantieparken campings campings campings nederland vakantieverblijf beach house bungalow chalet groepsaccommodatie lodge strandhuis villa verblijf last minutes midweek weg weekendje weg weekje weg service & contact bekijk de veelgestelde vragen &nbsp;of neem con",
      "textLength": 8736
    },
    "evaluation": {
      "score": 5,
      "confidence": "low",
      "reasoning": "Algemeen als kindvriendelijk genoemd maar geen concrete voorzieningen voor peuters vermeld.",
      "has_play_area": null,
      "has_high_chairs": null,
      "has_kids_menu": null,
      "has_diaper_changing": null,
      "weather": "outdoor",
      "description": null,
      "toddler_highlight": null,
      "is_pancake_restaurant": false
    }
  },
  {
    "osm_id": 286715263,
    "osm_type": "way",
    "name": "Paviljoen SOUT",
    "amenity": "restaurant",
    "lat": 52.4931934,
    "lng": 4.5849551,
    "address": "Strand Zuiderbad 80",
    "city": "Wijk aan Zee",
    "website": "https://sout.nl/",
    "phone": null,
    "cuisine": null,
    "outdoor_seating": null,
    "wheelchair": "yes",
    "opening_hours": null,
    "scrape": {
      "success": true,
      "keywords": [],
      "snippet": null,
      "textLength": 1039
    },
    "evaluation": {
      "score": 4,
      "confidence": "low",
      "reasoning": "Geen website-aanwijzingen gevonden voor kindvriendelijkheid.",
      "has_play_area": null,
      "has_high_chairs": null,
      "has_kids_menu": null,
      "has_diaper_changing": null,
      "weather": null,
      "description": null,
      "toddler_highlight": null,
      "is_pancake_restaurant": false
    }
  },
  {
    "osm_id": 286715794,
    "osm_type": "way",
    "name": "Fletcher Hotel-Restaurant Zeeduin",
    "amenity": "restaurant",
    "lat": 52.4976049,
    "lng": 4.5894102,
    "address": "Relweg 59",
    "city": "Wijk aan Zee",
    "website": "https://www.hotelzeeduin.nl/",
    "phone": null,
    "cuisine": null,
    "outdoor_seating": null,
    "wheelchair": null,
    "opening_hours": null,
    "scrape": {
      "success": true,
      "keywords": [
        "kinderen",
        "kids",
        "baby"
      ],
      "snippet": "40 03 € 99,90 04 € 109,40 2 05 € 104,65 2 2 minimaal aantal nachten prijzen zijn per persoon per nacht. exclusief ontbijt. wie gaan er mee? 1 kamer voor 2 volwassenen kamers aantal volwassenen aantal kinderen 4 - 11 jaar aantal baby's 0 - 3 jaar wijzigen aantal nachten fletcher hotel-restaurant zeeduin modern hotel gelegen op 50 meter afstand van het breedste strand van noord-holland boek een kamer booking.com 7.6 expedia.nl 8.2 google 7.8 review score 7, 8 classificering let op: vanaf 18-02-202",
      "textLength": 5542
    },
    "evaluation": {
      "score": 5,
      "confidence": "low",
      "reasoning": "Hotel-restaurant met mogelijkheid voor baby's (0-3 jaar) maar geen concrete kindvriendelijke voorzieningen gespecificeerd.",
      "has_play_area": null,
      "has_high_chairs": null,
      "has_kids_menu": null,
      "has_diaper_changing": null,
      "weather": "indoor",
      "description": null,
      "toddler_highlight": null,
      "is_pancake_restaurant": false
    }
  },
  {
    "osm_id": 967792479,
    "osm_type": "node",
    "name": "De Open Keuken",
    "amenity": "restaurant",
    "lat": 52.4846521,
    "lng": 4.6471514,
    "address": "Duinwijklaan 35",
    "city": "Beverwijk",
    "website": null,
    "phone": null,
    "cuisine": null,
    "outdoor_seating": null,
    "wheelchair": null,
    "opening_hours": null,
    "scrape": {
      "success": false,
      "error": "no_website",
      "keywords": [],
      "snippet": null
    },
    "evaluation": {
      "score": 4,
      "confidence": "low",
      "reasoning": "Geen website-aanwijzingen gevonden voor kindvriendelijkheid.",
      "has_play_area": null,
      "has_high_chairs": null,
      "has_kids_menu": null,
      "has_diaper_changing": null,
      "weather": null,
      "description": null,
      "toddler_highlight": null,
      "is_pancake_restaurant": false
    }
  },
  {
    "osm_id": 967792818,
    "osm_type": "node",
    "name": "De Jonge Halewijn",
    "amenity": "restaurant",
    "lat": 52.4847315,
    "lng": 4.6483572,
    "address": "Duinwijklaan 46",
    "city": "Beverwijk",
    "website": null,
    "phone": null,
    "cuisine": null,
    "outdoor_seating": null,
    "wheelchair": null,
    "opening_hours": null,
    "scrape": {
      "success": false,
      "error": "no_website",
      "keywords": [],
      "snippet": null
    },
    "evaluation": {
      "score": 4,
      "confidence": "low",
      "reasoning": "Geen website-aanwijzingen gevonden voor kindvriendelijkheid.",
      "has_play_area": null,
      "has_high_chairs": null,
      "has_kids_menu": null,
      "has_diaper_changing": null,
      "weather": null,
      "description": null,
      "toddler_highlight": null,
      "is_pancake_restaurant": false
    }
  },
  {
    "osm_id": 983308052,
    "osm_type": "node",
    "name": "Golden House",
    "amenity": "restaurant",
    "lat": 52.4825756,
    "lng": 4.6514258,
    "address": "Zeestraat 77",
    "city": "Beverwijk",
    "website": null,
    "phone": null,
    "cuisine": "chinese",
    "outdoor_seating": null,
    "wheelchair": null,
    "opening_hours": null,
    "scrape": {
      "success": false,
      "error": "no_website",
      "keywords": [],
      "snippet": null
    },
    "evaluation": {
      "score": 4,
      "confidence": "low",
      "reasoning": "Geen website-aanwijzingen gevonden voor kindvriendelijkheid.",
      "has_play_area": null,
      "has_high_chairs": null,
      "has_kids_menu": null,
      "has_diaper_changing": null,
      "weather": null,
      "description": null,
      "toddler_highlight": null,
      "is_pancake_restaurant": false
    }
  },
  {
    "osm_id": 2538555305,
    "osm_type": "node",
    "name": "The Döner Company",
    "amenity": "fast_food",
    "lat": 52.4784037,
    "lng": 4.6555651,
    "address": null,
    "city": null,
    "website": null,
    "phone": null,
    "cuisine": "kebab",
    "outdoor_seating": null,
    "wheelchair": null,
    "opening_hours": null,
    "scrape": {
      "success": false,
      "error": "no_website",
      "keywords": [],
      "snippet": null
    },
    "evaluation": {
      "score": 4,
      "confidence": "low",
      "reasoning": "Geen website-aanwijzingen gevonden voor kindvriendelijkheid.",
      "has_play_area": null,
      "has_high_chairs": null,
      "has_kids_menu": null,
      "has_diaper_changing": null,
      "weather": null,
      "description": null,
      "toddler_highlight": null,
      "is_pancake_restaurant": false
    }
  },
  {
    "osm_id": 2903927541,
    "osm_type": "node",
    "name": "Antalya",
    "amenity": "fast_food",
    "lat": 52.4922734,
    "lng": 4.590246,
    "address": "de Zwaanstraat 10",
    "city": "Wijk aan Zee",
    "website": null,
    "phone": null,
    "cuisine": "kebab",
    "outdoor_seating": null,
    "wheelchair": null,
    "opening_hours": null,
    "scrape": {
      "success": false,
      "error": "no_website",
      "keywords": [],
      "snippet": null
    },
    "evaluation": {
      "score": 4,
      "confidence": "low",
      "reasoning": "Geen website-aanwijzingen gevonden voor kindvriendelijkheid.",
      "has_play_area": null,
      "has_high_chairs": null,
      "has_kids_menu": null,
      "has_diaper_changing": null,
      "weather": null,
      "description": null,
      "toddler_highlight": null,
      "is_pancake_restaurant": false
    }
  },
  {
    "osm_id": 2903927621,
    "osm_type": "node",
    "name": "De Liefhebbers",
    "amenity": "restaurant",
    "lat": 52.4922054,
    "lng": 4.5908215,
    "address": "de Zwaanstraat 20-bene",
    "city": "Wijk aan Zee",
    "website": null,
    "phone": null,
    "cuisine": null,
    "outdoor_seating": null,
    "wheelchair": null,
    "opening_hours": null,
    "scrape": {
      "success": false,
      "error": "no_website",
      "keywords": [],
      "snippet": null
    },
    "evaluation": {
      "score": 4,
      "confidence": "low",
      "reasoning": "Geen website-aanwijzingen gevonden voor kindvriendelijkheid.",
      "has_play_area": null,
      "has_high_chairs": null,
      "has_kids_menu": null,
      "has_diaper_changing": null,
      "weather": null,
      "description": null,
      "toddler_highlight": null,
      "is_pancake_restaurant": false
    }
  },
  {
    "osm_id": 2903930109,
    "osm_type": "node",
    "name": "De IJsgalerij",
    "amenity": "ice_cream",
    "lat": 52.4921525,
    "lng": 4.5909697,
    "address": "de Zwaanstraat 22",
    "city": "Wijk aan Zee",
    "website": null,
    "phone": null,
    "cuisine": null,
    "outdoor_seating": null,
    "wheelchair": null,
    "opening_hours": null,
    "scrape": {
      "success": false,
      "error": "no_website",
      "keywords": [],
      "snippet": null
    },
    "evaluation": {
      "score": 4,
      "confidence": "low",
      "reasoning": "Geen website-aanwijzingen gevonden voor kindvriendelijkheid.",
      "has_play_area": null,
      "has_high_chairs": null,
      "has_kids_menu": null,
      "has_diaper_changing": null,
      "weather": null,
      "description": null,
      "toddler_highlight": null,
      "is_pancake_restaurant": false
    }
  },
  {
    "osm_id": 2903930280,
    "osm_type": "node",
    "name": "Restaurant Efes",
    "amenity": "restaurant",
    "lat": 52.4939159,
    "lng": 4.5939271,
    "address": "Verlengde Voorstraat 2A",
    "city": "Wijk aan Zee",
    "website": null,
    "phone": null,
    "cuisine": null,
    "outdoor_seating": null,
    "wheelchair": null,
    "opening_hours": null,
    "scrape": {
      "success": false,
      "error": "no_website",
      "keywords": [],
      "snippet": null
    },
    "evaluation": {
      "score": 4,
      "confidence": "low",
      "reasoning": "Geen website-aanwijzingen gevonden voor kindvriendelijkheid.",
      "has_play_area": null,
      "has_high_chairs": null,
      "has_kids_menu": null,
      "has_diaper_changing": null,
      "weather": null,
      "description": null,
      "toddler_highlight": null,
      "is_pancake_restaurant": false
    }
  },
  {
    "osm_id": 2903930303,
    "osm_type": "node",
    "name": "Onder de Toren",
    "amenity": "fast_food",
    "lat": 52.492329,
    "lng": 4.5918353,
    "address": "Voorstraat 3",
    "city": "Wijk aan Zee",
    "website": null,
    "phone": null,
    "cuisine": null,
    "outdoor_seating": null,
    "wheelchair": null,
    "opening_hours": null,
    "scrape": {
      "success": false,
      "error": "no_website",
      "keywords": [],
      "snippet": null
    },
    "evaluation": {
      "score": 4,
      "confidence": "low",
      "reasoning": "Geen website-aanwijzingen gevonden voor kindvriendelijkheid.",
      "has_play_area": null,
      "has_high_chairs": null,
      "has_kids_menu": null,
      "has_diaper_changing": null,
      "weather": null,
      "description": null,
      "toddler_highlight": null,
      "is_pancake_restaurant": false
    }
  },
  {
    "osm_id": 2903931198,
    "osm_type": "node",
    "name": "Snackcorner",
    "amenity": "fast_food",
    "lat": 52.4924588,
    "lng": 4.5924219,
    "address": "Julianaplein 49",
    "city": "Wijk aan Zee",
    "website": null,
    "phone": null,
    "cuisine": null,
    "outdoor_seating": null,
    "wheelchair": null,
    "opening_hours": null,
    "scrape": {
      "success": false,
      "error": "no_website",
      "keywords": [],
      "snippet": null
    },
    "evaluation": {
      "score": 4,
      "confidence": "low",
      "reasoning": "Geen website-aanwijzingen gevonden voor kindvriendelijkheid.",
      "has_play_area": null,
      "has_high_chairs": null,
      "has_kids_menu": null,
      "has_diaper_changing": null,
      "weather": null,
      "description": null,
      "toddler_highlight": null,
      "is_pancake_restaurant": false
    }
  },
  {
    "osm_id": 2903931257,
    "osm_type": "node",
    "name": "Brasserie Klein Zwitserland",
    "amenity": "cafe",
    "lat": 52.4925238,
    "lng": 4.5922927,
    "address": "Julianaplein 53",
    "city": "Wijk aan Zee",
    "website": null,
    "phone": null,
    "cuisine": null,
    "outdoor_seating": null,
    "wheelchair": null,
    "opening_hours": null,
    "scrape": {
      "success": false,
      "error": "no_website",
      "keywords": [],
      "snippet": null
    },
    "evaluation": {
      "score": 4,
      "confidence": "low",
      "reasoning": "Geen website-aanwijzingen gevonden voor kindvriendelijkheid.",
      "has_play_area": null,
      "has_high_chairs": null,
      "has_kids_menu": null,
      "has_diaper_changing": null,
      "weather": null,
      "description": null,
      "toddler_highlight": null,
      "is_pancake_restaurant": false
    }
  },
  {
    "osm_id": 2903931850,
    "osm_type": "node",
    "name": "Gewoon in Wijk aan Zee",
    "amenity": "restaurant",
    "lat": 52.4922818,
    "lng": 4.5901575,
    "address": "de Zwaanstraat 8",
    "city": "Wijk aan Zee",
    "website": null,
    "phone": null,
    "cuisine": null,
    "outdoor_seating": null,
    "wheelchair": null,
    "opening_hours": null,
    "scrape": {
      "success": false,
      "error": "no_website",
      "keywords": [],
      "snippet": null
    },
    "evaluation": {
      "score": 4,
      "confidence": "low",
      "reasoning": "Geen website-aanwijzingen gevonden voor kindvriendelijkheid.",
      "has_play_area": null,
      "has_high_chairs": null,
      "has_kids_menu": null,
      "has_diaper_changing": null,
      "weather": null,
      "description": null,
      "toddler_highlight": null,
      "is_pancake_restaurant": false
    }
  },
  {
    "osm_id": 2905209095,
    "osm_type": "node",
    "name": "La Vanessa",
    "amenity": "fast_food",
    "lat": 52.4975706,
    "lng": 4.6578324,
    "address": "Alkmaarseweg 462",
    "city": "Beverwijk",
    "website": null,
    "phone": null,
    "cuisine": "italian",
    "outdoor_seating": null,
    "wheelchair": null,
    "opening_hours": null,
    "scrape": {
      "success": false,
      "error": "no_website",
      "keywords": [],
      "snippet": null
    },
    "evaluation": {
      "score": 4,
      "confidence": "low",
      "reasoning": "Geen website-aanwijzingen gevonden voor kindvriendelijkheid.",
      "has_play_area": null,
      "has_high_chairs": null,
      "has_kids_menu": null,
      "has_diaper_changing": null,
      "weather": null,
      "description": null,
      "toddler_highlight": null,
      "is_pancake_restaurant": false
    }
  },
  {
    "osm_id": 2907018742,
    "osm_type": "node",
    "name": "Toffe Jongens",
    "amenity": "cafe",
    "lat": 52.479333,
    "lng": 4.6619605,
    "address": "Parallelweg 110",
    "city": "Beverwijk",
    "website": null,
    "phone": null,
    "cuisine": null,
    "outdoor_seating": null,
    "wheelchair": null,
    "opening_hours": null,
    "scrape": {
      "success": false,
      "error": "no_website",
      "keywords": [],
      "snippet": null
    },
    "evaluation": {
      "score": 4,
      "confidence": "low",
      "reasoning": "Geen website-aanwijzingen gevonden voor kindvriendelijkheid.",
      "has_play_area": null,
      "has_high_chairs": null,
      "has_kids_menu": null,
      "has_diaper_changing": null,
      "weather": null,
      "description": null,
      "toddler_highlight": null,
      "is_pancake_restaurant": false
    }
  },
  {
    "osm_id": 2907019587,
    "osm_type": "node",
    "name": "Budget Broodjes",
    "amenity": "fast_food",
    "lat": 52.4753558,
    "lng": 4.6582725,
    "address": "Rietlanden 5",
    "city": "Beverwijk",
    "website": null,
    "phone": null,
    "cuisine": "sandwich",
    "outdoor_seating": null,
    "wheelchair": null,
    "opening_hours": null,
    "scrape": {
      "success": false,
      "error": "no_website",
      "keywords": [],
      "snippet": null
    },
    "evaluation": {
      "score": 4,
      "confidence": "low",
      "reasoning": "Geen website-aanwijzingen gevonden voor kindvriendelijkheid.",
      "has_play_area": null,
      "has_high_chairs": null,
      "has_kids_menu": null,
      "has_diaper_changing": null,
      "weather": null,
      "description": null,
      "toddler_highlight": null,
      "is_pancake_restaurant": false
    }
  },
  {
    "osm_id": 2909054694,
    "osm_type": "node",
    "name": "Eethuis 't Smitje",
    "amenity": "fast_food",
    "lat": 52.4933484,
    "lng": 4.6789291,
    "address": "Belgiëlaan 37A",
    "city": "Beverwijk",
    "website": null,
    "phone": null,
    "cuisine": null,
    "outdoor_seating": null,
    "wheelchair": null,
    "opening_hours": "Mo-Su 15:00-23:00",
    "scrape": {
      "success": false,
      "error": "no_website",
      "keywords": [],
      "snippet": null
    },
    "evaluation": {
      "score": 4,
      "confidence": "low",
      "reasoning": "Geen website-aanwijzingen gevonden voor kindvriendelijkheid.",
      "has_play_area": null,
      "has_high_chairs": null,
      "has_kids_menu": null,
      "has_diaper_changing": null,
      "weather": null,
      "description": null,
      "toddler_highlight": null,
      "is_pancake_restaurant": false
    }
  },
  {
    "osm_id": 2909579389,
    "osm_type": "node",
    "name": "Sportcafe de Walvis",
    "amenity": "cafe",
    "lat": 52.4914354,
    "lng": 4.6657375,
    "address": "Van Loenenlaan 1-bove",
    "city": "Beverwijk",
    "website": null,
    "phone": null,
    "cuisine": null,
    "outdoor_seating": null,
    "wheelchair": "yes",
    "opening_hours": null,
    "scrape": {
      "success": false,
      "error": "no_website",
      "keywords": [],
      "snippet": null
    },
    "evaluation": {
      "score": 4,
      "confidence": "low",
      "reasoning": "Geen website-aanwijzingen gevonden voor kindvriendelijkheid.",
      "has_play_area": null,
      "has_high_chairs": null,
      "has_kids_menu": null,
      "has_diaper_changing": null,
      "weather": null,
      "description": null,
      "toddler_highlight": null,
      "is_pancake_restaurant": false
    }
  },
  {
    "osm_id": 2909579662,
    "osm_type": "node",
    "name": "Portofino",
    "amenity": "fast_food",
    "lat": 52.4873777,
    "lng": 4.6606213,
    "address": "Alkmaarseweg 101",
    "city": "Beverwijk",
    "website": null,
    "phone": null,
    "cuisine": "pizza",
    "outdoor_seating": null,
    "wheelchair": null,
    "opening_hours": null,
    "scrape": {
      "success": false,
      "error": "no_website",
      "keywords": [],
      "snippet": null
    },
    "evaluation": {
      "score": 4,
      "confidence": "low",
      "reasoning": "Geen website-aanwijzingen gevonden voor kindvriendelijkheid.",
      "has_play_area": null,
      "has_high_chairs": null,
      "has_kids_menu": null,
      "has_diaper_changing": null,
      "weather": null,
      "description": null,
      "toddler_highlight": null,
      "is_pancake_restaurant": false
    }
  },
  {
    "osm_id": 2909579692,
    "osm_type": "node",
    "name": "Podium 104",
    "amenity": "cafe",
    "lat": 52.4905077,
    "lng": 4.6668864,
    "address": "Hoflanderweg 104",
    "city": "Beverwijk",
    "website": null,
    "phone": null,
    "cuisine": null,
    "outdoor_seating": null,
    "wheelchair": "limited",
    "opening_hours": null,
    "scrape": {
      "success": false,
      "error": "no_website",
      "keywords": [],
      "snippet": null
    },
    "evaluation": {
      "score": 4,
      "confidence": "low",
      "reasoning": "Geen website-aanwijzingen gevonden voor kindvriendelijkheid.",
      "has_play_area": null,
      "has_high_chairs": null,
      "has_kids_menu": null,
      "has_diaper_changing": null,
      "weather": null,
      "description": null,
      "toddler_highlight": null,
      "is_pancake_restaurant": false
    }
  },
  {
    "osm_id": 2909580003,
    "osm_type": "node",
    "name": "Grillroom Mario",
    "amenity": "restaurant",
    "lat": 52.487413,
    "lng": 4.6606095,
    "address": "Alkmaarseweg 105",
    "city": "Beverwijk",
    "website": null,
    "phone": null,
    "cuisine": "grill",
    "outdoor_seating": null,
    "wheelchair": null,
    "opening_hours": null,
    "scrape": {
      "success": false,
      "error": "no_website",
      "keywords": [],
      "snippet": null
    },
    "evaluation": {
      "score": 4,
      "confidence": "low",
      "reasoning": "Geen website-aanwijzingen gevonden voor kindvriendelijkheid.",
      "has_play_area": null,
      "has_high_chairs": null,
      "has_kids_menu": null,
      "has_diaper_changing": null,
      "weather": null,
      "description": null,
      "toddler_highlight": null,
      "is_pancake_restaurant": false
    }
  },
  {
    "osm_id": 2909581163,
    "osm_type": "node",
    "name": "Pizza Service",
    "amenity": "fast_food",
    "lat": 52.488922,
    "lng": 4.6603603,
    "address": "Alkmaarseweg 139",
    "city": "Beverwijk",
    "website": null,
    "phone": null,
    "cuisine": "pizza",
    "outdoor_seating": null,
    "wheelchair": null,
    "opening_hours": null,
    "scrape": {
      "success": false,
      "error": "no_website",
      "keywords": [],
      "snippet": null
    },
    "evaluation": {
      "score": 4,
      "confidence": "low",
      "reasoning": "Geen website-aanwijzingen gevonden voor kindvriendelijkheid.",
      "has_play_area": null,
      "has_high_chairs": null,
      "has_kids_menu": null,
      "has_diaper_changing": null,
      "weather": null,
      "description": null,
      "toddler_highlight": null,
      "is_pancake_restaurant": false
    }
  },
  {
    "osm_id": 2909590662,
    "osm_type": "node",
    "name": "Hong Fa",
    "amenity": "restaurant",
    "lat": 52.4964822,
    "lng": 4.6635493,
    "address": "President Kennedyplein 4",
    "city": "Beverwijk",
    "website": null,
    "phone": null,
    "cuisine": "chinese",
    "outdoor_seating": null,
    "wheelchair": "yes",
    "opening_hours": null,
    "scrape": {
      "success": false,
      "error": "no_website",
      "keywords": [],
      "snippet": null
    },
    "evaluation": {
      "score": 4,
      "confidence": "low",
      "reasoning": "Geen website-aanwijzingen gevonden voor kindvriendelijkheid.",
      "has_play_area": null,
      "has_high_chairs": null,
      "has_kids_menu": null,
      "has_diaper_changing": null,
      "weather": null,
      "description": null,
      "toddler_highlight": null,
      "is_pancake_restaurant": false
    }
  },
  {
    "osm_id": 2909592899,
    "osm_type": "node",
    "name": "Millennium Internet Cafe",
    "amenity": "cafe",
    "lat": 52.4854461,
    "lng": 4.6636858,
    "address": "Hendrik Mandeweg 41",
    "city": "Beverwijk",
    "website": null,
    "phone": null,
    "cuisine": null,
    "outdoor_seating": null,
    "wheelchair": null,
    "opening_hours": null,
    "scrape": {
      "success": false,
      "error": "no_website",
      "keywords": [],
      "snippet": null
    },
    "evaluation": {
      "score": 4,
      "confidence": "low",
      "reasoning": "Geen website-aanwijzingen gevonden voor kindvriendelijkheid.",
      "has_play_area": null,
      "has_high_chairs": null,
      "has_kids_menu": null,
      "has_diaper_changing": null,
      "weather": null,
      "description": null,
      "toddler_highlight": null,
      "is_pancake_restaurant": false
    }
  },
  {
    "osm_id": 2909593442,
    "osm_type": "node",
    "name": "Café Efe's",
    "amenity": "cafe",
    "lat": 52.4852075,
    "lng": 4.66288,
    "address": "Hendrik Mandeweg 42",
    "city": "Beverwijk",
    "website": null,
    "phone": null,
    "cuisine": null,
    "outdoor_seating": null,
    "wheelchair": null,
    "opening_hours": null,
    "scrape": {
      "success": false,
      "error": "no_website",
      "keywords": [],
      "snippet": null
    },
    "evaluation": {
      "score": 4,
      "confidence": "low",
      "reasoning": "Geen website-aanwijzingen gevonden voor kindvriendelijkheid.",
      "has_play_area": null,
      "has_high_chairs": null,
      "has_kids_menu": null,
      "has_diaper_changing": null,
      "weather": null,
      "description": null,
      "toddler_highlight": null,
      "is_pancake_restaurant": false
    }
  },
  {
    "osm_id": 2909594526,
    "osm_type": "node",
    "name": "Cafe Baran",
    "amenity": "cafe",
    "lat": 52.4852352,
    "lng": 4.6629131,
    "address": "Hendrik Mandeweg 44",
    "city": "Beverwijk",
    "website": null,
    "phone": null,
    "cuisine": null,
    "outdoor_seating": null,
    "wheelchair": null,
    "opening_hours": null,
    "scrape": {
      "success": false,
      "error": "no_website",
      "keywords": [],
      "snippet": null
    },
    "evaluation": {
      "score": 4,
      "confidence": "low",
      "reasoning": "Geen website-aanwijzingen gevonden voor kindvriendelijkheid.",
      "has_play_area": null,
      "has_high_chairs": null,
      "has_kids_menu": null,
      "has_diaper_changing": null,
      "weather": null,
      "description": null,
      "toddler_highlight": null,
      "is_pancake_restaurant": false
    }
  },
  {
    "osm_id": 2909594539,
    "osm_type": "node",
    "name": "Shalom",
    "amenity": "fast_food",
    "lat": 52.4825177,
    "lng": 4.6624677,
    "address": "Schans 44",
    "city": "Beverwijk",
    "website": null,
    "phone": null,
    "cuisine": "shawarma",
    "outdoor_seating": null,
    "wheelchair": null,
    "opening_hours": null,
    "scrape": {
      "success": false,
      "error": "no_website",
      "keywords": [],
      "snippet": null
    },
    "evaluation": {
      "score": 4,
      "confidence": "low",
      "reasoning": "Geen website-aanwijzingen gevonden voor kindvriendelijkheid.",
      "has_play_area": null,
      "has_high_chairs": null,
      "has_kids_menu": null,
      "has_diaper_changing": null,
      "weather": null,
      "description": null,
      "toddler_highlight": null,
      "is_pancake_restaurant": false
    }
  },
  {
    "osm_id": 2909595655,
    "osm_type": "node",
    "name": "Patisserie Balkan",
    "amenity": "fast_food",
    "lat": 52.4855914,
    "lng": 4.663919,
    "address": "Hendrik Mandeweg 49",
    "city": "Beverwijk",
    "website": null,
    "phone": null,
    "cuisine": "kebab",
    "outdoor_seating": null,
    "wheelchair": null,
    "opening_hours": null,
    "scrape": {
      "success": false,
      "error": "no_website",
      "keywords": [],
      "snippet": null
    },
    "evaluation": {
      "score": 4,
      "confidence": "low",
      "reasoning": "Geen website-aanwijzingen gevonden voor kindvriendelijkheid.",
      "has_play_area": null,
      "has_high_chairs": null,
      "has_kids_menu": null,
      "has_diaper_changing": null,
      "weather": null,
      "description": null,
      "toddler_highlight": null,
      "is_pancake_restaurant": false
    }
  },
  {
    "osm_id": 2909598369,
    "osm_type": "node",
    "name": "Wijker Doner",
    "amenity": "fast_food",
    "lat": 52.4956648,
    "lng": 4.6651088,
    "address": "Büllerlaan 74",
    "city": "Beverwijk",
    "website": null,
    "phone": null,
    "cuisine": "kebab",
    "outdoor_seating": null,
    "wheelchair": null,
    "opening_hours": null,
    "scrape": {
      "success": false,
      "error": "no_website",
      "keywords": [],
      "snippet": null
    },
    "evaluation": {
      "score": 4,
      "confidence": "low",
      "reasoning": "Geen website-aanwijzingen gevonden voor kindvriendelijkheid.",
      "has_play_area": null,
      "has_high_chairs": null,
      "has_kids_menu": null,
      "has_diaper_changing": null,
      "weather": null,
      "description": null,
      "toddler_highlight": null,
      "is_pancake_restaurant": false
    }
  },
  {
    "osm_id": 2909605511,
    "osm_type": "node",
    "name": "Restaurant INGER",
    "amenity": "restaurant",
    "lat": 52.4955954,
    "lng": 4.6637599,
    "address": "Frank Sinatraplein 85",
    "city": "Beverwijk",
    "website": null,
    "phone": null,
    "cuisine": null,
    "outdoor_seating": null,
    "wheelchair": null,
    "opening_hours": null,
    "scrape": {
      "success": false,
      "error": "no_website",
      "keywords": [],
      "snippet": null
    },
    "evaluation": {
      "score": 4,
      "confidence": "low",
      "reasoning": "Geen website-aanwijzingen gevonden voor kindvriendelijkheid.",
      "has_play_area": null,
      "has_high_chairs": null,
      "has_kids_menu": null,
      "has_diaper_changing": null,
      "weather": null,
      "description": null,
      "toddler_highlight": null,
      "is_pancake_restaurant": false
    }
  },
  {
    "osm_id": 2909606504,
    "osm_type": "node",
    "name": "Fresco",
    "amenity": "fast_food",
    "lat": 52.4910684,
    "lng": 4.6615618,
    "address": "Heemskerkerweg 93",
    "city": "Beverwijk",
    "website": null,
    "phone": null,
    "cuisine": "pizza",
    "outdoor_seating": null,
    "wheelchair": null,
    "opening_hours": null,
    "scrape": {
      "success": false,
      "error": "no_website",
      "keywords": [],
      "snippet": null
    },
    "evaluation": {
      "score": 4,
      "confidence": "low",
      "reasoning": "Geen website-aanwijzingen gevonden voor kindvriendelijkheid.",
      "has_play_area": null,
      "has_high_chairs": null,
      "has_kids_menu": null,
      "has_diaper_changing": null,
      "weather": null,
      "description": null,
      "toddler_highlight": null,
      "is_pancake_restaurant": false
    }
  },
  {
    "osm_id": 2909606519,
    "osm_type": "node",
    "name": "Wok & Cool Sushi",
    "amenity": "restaurant",
    "lat": 52.487261,
    "lng": 4.6606379,
    "address": "Alkmaarseweg 95",
    "city": "Beverwijk",
    "website": null,
    "phone": null,
    "cuisine": "wok",
    "outdoor_seating": null,
    "wheelchair": null,
    "opening_hours": null,
    "scrape": {
      "success": false,
      "error": "no_website",
      "keywords": [],
      "snippet": null
    },
    "evaluation": {
      "score": 4,
      "confidence": "low",
      "reasoning": "Geen website-aanwijzingen gevonden voor kindvriendelijkheid.",
      "has_play_area": null,
      "has_high_chairs": null,
      "has_kids_menu": null,
      "has_diaper_changing": null,
      "weather": null,
      "description": null,
      "toddler_highlight": null,
      "is_pancake_restaurant": false
    }
  },
  {
    "osm_id": 2911208504,
    "osm_type": "node",
    "name": "Cafetaria Jimmy's",
    "amenity": "fast_food",
    "lat": 52.48097,
    "lng": 4.654853,
    "address": "Zeestraat 11",
    "city": "Beverwijk",
    "website": null,
    "phone": null,
    "cuisine": null,
    "outdoor_seating": null,
    "wheelchair": null,
    "opening_hours": null,
    "scrape": {
      "success": false,
      "error": "no_website",
      "keywords": [],
      "snippet": null
    },
    "evaluation": {
      "score": 4,
      "confidence": "low",
      "reasoning": "Geen website-aanwijzingen gevonden voor kindvriendelijkheid.",
      "has_play_area": null,
      "has_high_chairs": null,
      "has_kids_menu": null,
      "has_diaper_changing": null,
      "weather": null,
      "description": null,
      "toddler_highlight": null,
      "is_pancake_restaurant": false
    }
  },
  {
    "osm_id": 2911209201,
    "osm_type": "node",
    "name": "Dama Roze",
    "amenity": "restaurant",
    "lat": 52.4822682,
    "lng": 4.6584088,
    "address": "Breestraat 110",
    "city": "Beverwijk",
    "website": null,
    "phone": null,
    "cuisine": null,
    "outdoor_seating": null,
    "wheelchair": null,
    "opening_hours": null,
    "scrape": {
      "success": false,
      "error": "no_website",
      "keywords": [],
      "snippet": null
    },
    "evaluation": {
      "score": 4,
      "confidence": "low",
      "reasoning": "Geen website-aanwijzingen gevonden voor kindvriendelijkheid.",
      "has_play_area": null,
      "has_high_chairs": null,
      "has_kids_menu": null,
      "has_diaper_changing": null,
      "weather": null,
      "description": null,
      "toddler_highlight": null,
      "is_pancake_restaurant": false
    }
  },
  {
    "osm_id": 2911209552,
    "osm_type": "node",
    "name": "Domino's",
    "amenity": "fast_food",
    "lat": 52.4823953,
    "lng": 4.6586275,
    "address": "Breestraat 116",
    "city": "Beverwijk",
    "website": null,
    "phone": null,
    "cuisine": "pizza",
    "outdoor_seating": null,
    "wheelchair": null,
    "opening_hours": null,
    "scrape": {
      "success": false,
      "error": "no_website",
      "keywords": [],
      "snippet": null
    },
    "evaluation": {
      "score": 4,
      "confidence": "low",
      "reasoning": "Geen website-aanwijzingen gevonden voor kindvriendelijkheid.",
      "has_play_area": null,
      "has_high_chairs": null,
      "has_kids_menu": null,
      "has_diaper_changing": null,
      "weather": null,
      "description": null,
      "toddler_highlight": null,
      "is_pancake_restaurant": false
    }
  },
  {
    "osm_id": 2911209768,
    "osm_type": "node",
    "name": "Lunchroom Anders",
    "amenity": "cafe",
    "lat": 52.4825316,
    "lng": 4.6588608,
    "address": "Breestraat 122",
    "city": "Beverwijk",
    "website": null,
    "phone": null,
    "cuisine": null,
    "outdoor_seating": null,
    "wheelchair": null,
    "opening_hours": null,
    "scrape": {
      "success": false,
      "error": "no_website",
      "keywords": [],
      "snippet": null
    },
    "evaluation": {
      "score": 4,
      "confidence": "low",
      "reasoning": "Geen website-aanwijzingen gevonden voor kindvriendelijkheid.",
      "has_play_area": null,
      "has_high_chairs": null,
      "has_kids_menu": null,
      "has_diaper_changing": null,
      "weather": null,
      "description": null,
      "toddler_highlight": null,
      "is_pancake_restaurant": false
    }
  },
  {
    "osm_id": 2911212845,
    "osm_type": "node",
    "name": "Tramonti",
    "amenity": "restaurant",
    "lat": 52.4828757,
    "lng": 4.6594185,
    "address": "Breestraat 138",
    "city": "Beverwijk",
    "website": null,
    "phone": null,
    "cuisine": null,
    "outdoor_seating": null,
    "wheelchair": null,
    "opening_hours": null,
    "scrape": {
      "success": false,
      "error": "no_website",
      "keywords": [],
      "snippet": null
    },
    "evaluation": {
      "score": 4,
      "confidence": "low",
      "reasoning": "Geen website-aanwijzingen gevonden voor kindvriendelijkheid.",
      "has_play_area": null,
      "has_high_chairs": null,
      "has_kids_menu": null,
      "has_diaper_changing": null,
      "weather": null,
      "description": null,
      "toddler_highlight": null,
      "is_pancake_restaurant": false
    }
  },
  {
    "osm_id": 2911212852,
    "osm_type": "node",
    "name": "Eetcafé Amigo",
    "amenity": "fast_food",
    "lat": 52.4895154,
    "lng": 4.6501913,
    "address": "Plantage 138",
    "city": "Beverwijk",
    "website": null,
    "phone": null,
    "cuisine": null,
    "outdoor_seating": null,
    "wheelchair": null,
    "opening_hours": null,
    "scrape": {
      "success": false,
      "error": "no_website",
      "keywords": [],
      "snippet": null
    },
    "evaluation": {
      "score": 4,
      "confidence": "low",
      "reasoning": "Geen website-aanwijzingen gevonden voor kindvriendelijkheid.",
      "has_play_area": null,
      "has_high_chairs": null,
      "has_kids_menu": null,
      "has_diaper_changing": null,
      "weather": null,
      "description": null,
      "toddler_highlight": null,
      "is_pancake_restaurant": false
    }
  },
  {
    "osm_id": 2911214371,
    "osm_type": "node",
    "name": "Safi's Plek",
    "amenity": "restaurant",
    "lat": 52.4831581,
    "lng": 4.6598957,
    "address": "Breestraat 152",
    "city": "Beverwijk",
    "website": null,
    "phone": null,
    "cuisine": null,
    "outdoor_seating": null,
    "wheelchair": null,
    "opening_hours": null,
    "scrape": {
      "success": false,
      "error": "no_website",
      "keywords": [],
      "snippet": null
    },
    "evaluation": {
      "score": 4,
      "confidence": "low",
      "reasoning": "Geen website-aanwijzingen gevonden voor kindvriendelijkheid.",
      "has_play_area": null,
      "has_high_chairs": null,
      "has_kids_menu": null,
      "has_diaper_changing": null,
      "weather": null,
      "description": null,
      "toddler_highlight": null,
      "is_pancake_restaurant": false
    }
  },
  {
    "osm_id": 2911220606,
    "osm_type": "node",
    "name": "Subway",
    "amenity": "fast_food",
    "lat": 52.4796614,
    "lng": 4.6544828,
    "address": "Breestraat 2",
    "city": "Beverwijk",
    "website": null,
    "phone": null,
    "cuisine": "sandwich",
    "outdoor_seating": null,
    "wheelchair": null,
    "opening_hours": null,
    "scrape": {
      "success": false,
      "error": "no_website",
      "keywords": [],
      "snippet": null
    },
    "evaluation": {
      "score": 4,
      "confidence": "low",
      "reasoning": "Geen website-aanwijzingen gevonden voor kindvriendelijkheid.",
      "has_play_area": null,
      "has_high_chairs": null,
      "has_kids_menu": null,
      "has_diaper_changing": null,
      "weather": null,
      "description": null,
      "toddler_highlight": null,
      "is_pancake_restaurant": false
    }
  },
  {
    "osm_id": 2911221257,
    "osm_type": "node",
    "name": "Chinees Indisch Restaurant Azie",
    "amenity": "restaurant",
    "lat": 52.481119,
    "lng": 4.654247,
    "address": "Zeestraat 22",
    "city": "Beverwijk",
    "website": null,
    "phone": null,
    "cuisine": null,
    "outdoor_seating": null,
    "wheelchair": null,
    "opening_hours": null,
    "scrape": {
      "success": false,
      "error": "no_website",
      "keywords": [],
      "snippet": null
    },
    "evaluation": {
      "score": 4,
      "confidence": "low",
      "reasoning": "Geen website-aanwijzingen gevonden voor kindvriendelijkheid.",
      "has_play_area": null,
      "has_high_chairs": null,
      "has_kids_menu": null,
      "has_diaper_changing": null,
      "weather": null,
      "description": null,
      "toddler_highlight": null,
      "is_pancake_restaurant": false
    }
  },
  {
    "osm_id": 2911222007,
    "osm_type": "node",
    "name": "Saigon House",
    "amenity": "cafe",
    "lat": 52.4800286,
    "lng": 4.6557578,
    "address": "Breestraat 21",
    "city": "Beverwijk",
    "website": null,
    "phone": null,
    "cuisine": "vietnamese",
    "outdoor_seating": null,
    "wheelchair": null,
    "opening_hours": null,
    "scrape": {
      "success": false,
      "error": "no_website",
      "keywords": [],
      "snippet": null
    },
    "evaluation": {
      "score": 4,
      "confidence": "low",
      "reasoning": "Geen website-aanwijzingen gevonden voor kindvriendelijkheid.",
      "has_play_area": null,
      "has_high_chairs": null,
      "has_kids_menu": null,
      "has_diaper_changing": null,
      "weather": null,
      "description": null,
      "toddler_highlight": null,
      "is_pancake_restaurant": false
    }
  },
  {
    "osm_id": 2911227115,
    "osm_type": "node",
    "name": "The Reload",
    "amenity": "cafe",
    "lat": 52.4802183,
    "lng": 4.6553807,
    "address": "Breestraat 26",
    "city": "Beverwijk",
    "website": null,
    "phone": null,
    "cuisine": "coffee_shop",
    "outdoor_seating": null,
    "wheelchair": null,
    "opening_hours": null,
    "scrape": {
      "success": false,
      "error": "no_website",
      "keywords": [],
      "snippet": null
    },
    "evaluation": {
      "score": 4,
      "confidence": "low",
      "reasoning": "Geen website-aanwijzingen gevonden voor kindvriendelijkheid.",
      "has_play_area": null,
      "has_high_chairs": null,
      "has_kids_menu": null,
      "has_diaper_changing": null,
      "weather": null,
      "description": null,
      "toddler_highlight": null,
      "is_pancake_restaurant": false
    }
  },
  {
    "osm_id": 2911230033,
    "osm_type": "node",
    "name": "Snackbar Kuenenplein",
    "amenity": "fast_food",
    "lat": 52.4925057,
    "lng": 4.6555895,
    "address": "Kuenenplein 3",
    "city": "Beverwijk",
    "website": null,
    "phone": null,
    "cuisine": "snackbar",
    "outdoor_seating": null,
    "wheelchair": null,
    "opening_hours": null,
    "scrape": {
      "success": false,
      "error": "no_website",
      "keywords": [],
      "snippet": null
    },
    "evaluation": {
      "score": 4,
      "confidence": "low",
      "reasoning": "Geen website-aanwijzingen gevonden voor kindvriendelijkheid.",
      "has_play_area": null,
      "has_high_chairs": null,
      "has_kids_menu": null,
      "has_diaper_changing": null,
      "weather": null,
      "description": null,
      "toddler_highlight": null,
      "is_pancake_restaurant": false
    }
  },
  {
    "osm_id": 2911231887,
    "osm_type": "node",
    "name": "Deniz Döner & Pizzeria",
    "amenity": "fast_food",
    "lat": 52.4805141,
    "lng": 4.655258,
    "address": "Zeestraat 2B",
    "city": "Beverwijk",
    "website": null,
    "phone": null,
    "cuisine": "kebab;pizza",
    "outdoor_seating": null,
    "wheelchair": null,
    "opening_hours": null,
    "scrape": {
      "success": false,
      "error": "no_website",
      "keywords": [],
      "snippet": null
    },
    "evaluation": {
      "score": 4,
      "confidence": "low",
      "reasoning": "Geen website-aanwijzingen gevonden voor kindvriendelijkheid.",
      "has_play_area": null,
      "has_high_chairs": null,
      "has_kids_menu": null,
      "has_diaper_changing": null,
      "weather": null,
      "description": null,
      "toddler_highlight": null,
      "is_pancake_restaurant": false
    }
  },
  {
    "osm_id": 2911233662,
    "osm_type": "node",
    "name": "Zorba de Griek",
    "amenity": "restaurant",
    "lat": 52.4796657,
    "lng": 4.6561259,
    "address": "Meerstraat 32",
    "city": "Beverwijk",
    "website": null,
    "phone": null,
    "cuisine": null,
    "outdoor_seating": null,
    "wheelchair": "yes",
    "opening_hours": null,
    "scrape": {
      "success": false,
      "error": "no_website",
      "keywords": [],
      "snippet": null
    },
    "evaluation": {
      "score": 4,
      "confidence": "low",
      "reasoning": "Geen website-aanwijzingen gevonden voor kindvriendelijkheid.",
      "has_play_area": null,
      "has_high_chairs": null,
      "has_kids_menu": null,
      "has_diaper_changing": null,
      "weather": null,
      "description": null,
      "toddler_highlight": null,
      "is_pancake_restaurant": false
    }
  },
  {
    "osm_id": 2911238978,
    "osm_type": "node",
    "name": "Cafetaria Eethuis Luc Hof",
    "amenity": "fast_food",
    "lat": 52.4875916,
    "lng": 4.6544783,
    "address": "Boeweg 87",
    "city": "Beverwijk",
    "website": null,
    "phone": null,
    "cuisine": null,
    "outdoor_seating": null,
    "wheelchair": null,
    "opening_hours": null,
    "scrape": {
      "success": false,
      "error": "no_website",
      "keywords": [],
      "snippet": null
    },
    "evaluation": {
      "score": 4,
      "confidence": "low",
      "reasoning": "Geen website-aanwijzingen gevonden voor kindvriendelijkheid.",
      "has_play_area": null,
      "has_high_chairs": null,
      "has_kids_menu": null,
      "has_diaper_changing": null,
      "weather": null,
      "description": null,
      "toddler_highlight": null,
      "is_pancake_restaurant": false
    }
  },
  {
    "osm_id": 2911239331,
    "osm_type": "node",
    "name": "Kathmandu Kitchen",
    "amenity": "restaurant",
    "lat": 52.4821447,
    "lng": 4.6573362,
    "address": "Begijnenstraat 4",
    "city": "Beverwijk",
    "website": null,
    "phone": null,
    "cuisine": null,
    "outdoor_seating": null,
    "wheelchair": null,
    "opening_hours": null,
    "scrape": {
      "success": false,
      "error": "no_website",
      "keywords": [],
      "snippet": null
    },
    "evaluation": {
      "score": 4,
      "confidence": "low",
      "reasoning": "Geen website-aanwijzingen gevonden voor kindvriendelijkheid.",
      "has_play_area": null,
      "has_high_chairs": null,
      "has_kids_menu": null,
      "has_diaper_changing": null,
      "weather": null,
      "description": null,
      "toddler_highlight": null,
      "is_pancake_restaurant": false
    }
  },
  {
    "osm_id": 2911239773,
    "osm_type": "node",
    "name": "Brasserie Premiere",
    "amenity": "restaurant",
    "lat": 52.4808289,
    "lng": 4.6582117,
    "address": "Nieuwstraat 4",
    "city": "Beverwijk",
    "website": null,
    "phone": null,
    "cuisine": null,
    "outdoor_seating": null,
    "wheelchair": null,
    "opening_hours": null,
    "scrape": {
      "success": false,
      "error": "no_website",
      "keywords": [],
      "snippet": null
    },
    "evaluation": {
      "score": 4,
      "confidence": "low",
      "reasoning": "Geen website-aanwijzingen gevonden voor kindvriendelijkheid.",
      "has_play_area": null,
      "has_high_chairs": null,
      "has_kids_menu": null,
      "has_diaper_changing": null,
      "weather": null,
      "description": null,
      "toddler_highlight": null,
      "is_pancake_restaurant": false
    }
  },
  {
    "osm_id": 2911247335,
    "osm_type": "node",
    "name": "Sea Heaven",
    "amenity": "restaurant",
    "lat": 52.4826313,
    "lng": 4.6517193,
    "address": "Groenelaan 5",
    "city": "Beverwijk",
    "website": null,
    "phone": null,
    "cuisine": "chinese",
    "outdoor_seating": null,
    "wheelchair": null,
    "opening_hours": null,
    "scrape": {
      "success": false,
      "error": "no_website",
      "keywords": [],
      "snippet": null
    },
    "evaluation": {
      "score": 4,
      "confidence": "low",
      "reasoning": "Geen website-aanwijzingen gevonden voor kindvriendelijkheid.",
      "has_play_area": null,
      "has_high_chairs": null,
      "has_kids_menu": null,
      "has_diaper_changing": null,
      "weather": null,
      "description": null,
      "toddler_highlight": null,
      "is_pancake_restaurant": false
    }
  },
  {
    "osm_id": 2911248844,
    "osm_type": "node",
    "name": "New York Pizza",
    "amenity": "fast_food",
    "lat": 52.4859035,
    "lng": 4.6605719,
    "address": "Alkmaarseweg 54",
    "city": "Beverwijk",
    "website": null,
    "phone": null,
    "cuisine": "pizza",
    "outdoor_seating": null,
    "wheelchair": null,
    "opening_hours": null,
    "scrape": {
      "success": false,
      "error": "no_website",
      "keywords": [],
      "snippet": null
    },
    "evaluation": {
      "score": 4,
      "confidence": "low",
      "reasoning": "Geen website-aanwijzingen gevonden voor kindvriendelijkheid.",
      "has_play_area": null,
      "has_high_chairs": null,
      "has_kids_menu": null,
      "has_diaper_changing": null,
      "weather": null,
      "description": null,
      "toddler_highlight": null,
      "is_pancake_restaurant": false
    }
  },
  {
    "osm_id": 2911251546,
    "osm_type": "node",
    "name": "Marx O'Larry's",
    "amenity": "ice_cream",
    "lat": 52.4828115,
    "lng": 4.6521795,
    "address": "C.H. Moensstraat 65",
    "city": "Beverwijk",
    "website": null,
    "phone": null,
    "cuisine": null,
    "outdoor_seating": null,
    "wheelchair": null,
    "opening_hours": null,
    "scrape": {
      "success": false,
      "error": "no_website",
      "keywords": [],
      "snippet": null
    },
    "evaluation": {
      "score": 4,
      "confidence": "low",
      "reasoning": "Geen website-aanwijzingen gevonden voor kindvriendelijkheid.",
      "has_play_area": null,
      "has_high_chairs": null,
      "has_kids_menu": null,
      "has_diaper_changing": null,
      "weather": null,
      "description": null,
      "toddler_highlight": null,
      "is_pancake_restaurant": false
    }
  },
  {
    "osm_id": 2911254657,
    "osm_type": "node",
    "name": "Meli's Foodcorner",
    "amenity": "fast_food",
    "lat": 52.4827855,
    "lng": 4.6563098,
    "address": "Kloosterstraat 8",
    "city": "Beverwijk",
    "website": null,
    "phone": null,
    "cuisine": null,
    "outdoor_seating": null,
    "wheelchair": null,
    "opening_hours": null,
    "scrape": {
      "success": false,
      "error": "no_website",
      "keywords": [],
      "snippet": null
    },
    "evaluation": {
      "score": 4,
      "confidence": "low",
      "reasoning": "Geen website-aanwijzingen gevonden voor kindvriendelijkheid.",
      "has_play_area": null,
      "has_high_chairs": null,
      "has_kids_menu": null,
      "has_diaper_changing": null,
      "weather": null,
      "description": null,
      "toddler_highlight": null,
      "is_pancake_restaurant": false
    }
  },
  {
    "osm_id": 2911254659,
    "osm_type": "node",
    "name": "Koffiebar Splif",
    "amenity": "cafe",
    "lat": 52.4802151,
    "lng": 4.6547183,
    "address": "Koningstraat 8",
    "city": "Beverwijk",
    "website": null,
    "phone": null,
    "cuisine": null,
    "outdoor_seating": null,
    "wheelchair": null,
    "opening_hours": null,
    "scrape": {
      "success": false,
      "error": "no_website",
      "keywords": [],
      "snippet": null
    },
    "evaluation": {
      "score": 4,
      "confidence": "low",
      "reasoning": "Geen website-aanwijzingen gevonden voor kindvriendelijkheid.",
      "has_play_area": null,
      "has_high_chairs": null,
      "has_kids_menu": null,
      "has_diaper_changing": null,
      "weather": null,
      "description": null,
      "toddler_highlight": null,
      "is_pancake_restaurant": false
    }
  },
  {
    "osm_id": 2911254866,
    "osm_type": "node",
    "name": "SushiPoint",
    "amenity": "fast_food",
    "lat": 52.4806425,
    "lng": 4.6585975,
    "address": "Meerstraat 84",
    "city": "Beverwijk",
    "website": null,
    "phone": null,
    "cuisine": "sushi",
    "outdoor_seating": null,
    "wheelchair": null,
    "opening_hours": null,
    "scrape": {
      "success": false,
      "error": "no_website",
      "keywords": [],
      "snippet": null
    },
    "evaluation": {
      "score": 4,
      "confidence": "low",
      "reasoning": "Geen website-aanwijzingen gevonden voor kindvriendelijkheid.",
      "has_play_area": null,
      "has_high_chairs": null,
      "has_kids_menu": null,
      "has_diaper_changing": null,
      "weather": null,
      "description": null,
      "toddler_highlight": null,
      "is_pancake_restaurant": false
    }
  },
  {
    "osm_id": 2911255730,
    "osm_type": "node",
    "name": "City Snacks",
    "amenity": "fast_food",
    "lat": 52.4818637,
    "lng": 4.6584154,
    "address": "Breestraat 89",
    "city": "Beverwijk",
    "website": null,
    "phone": null,
    "cuisine": null,
    "outdoor_seating": null,
    "wheelchair": "yes",
    "opening_hours": null,
    "scrape": {
      "success": false,
      "error": "no_website",
      "keywords": [],
      "snippet": null
    },
    "evaluation": {
      "score": 4,
      "confidence": "low",
      "reasoning": "Geen website-aanwijzingen gevonden voor kindvriendelijkheid.",
      "has_play_area": null,
      "has_high_chairs": null,
      "has_kids_menu": null,
      "has_diaper_changing": null,
      "weather": null,
      "description": null,
      "toddler_highlight": null,
      "is_pancake_restaurant": false
    }
  },
  {
    "osm_id": 2911255791,
    "osm_type": "node",
    "name": "IJsfabrique",
    "amenity": "ice_cream",
    "lat": 52.4797862,
    "lng": 4.6552701,
    "address": "Breestraat 9",
    "city": "Beverwijk",
    "website": null,
    "phone": null,
    "cuisine": null,
    "outdoor_seating": null,
    "wheelchair": null,
    "opening_hours": null,
    "scrape": {
      "success": false,
      "error": "no_website",
      "keywords": [],
      "snippet": null
    },
    "evaluation": {
      "score": 4,
      "confidence": "low",
      "reasoning": "Geen website-aanwijzingen gevonden voor kindvriendelijkheid.",
      "has_play_area": null,
      "has_high_chairs": null,
      "has_kids_menu": null,
      "has_diaper_changing": null,
      "weather": null,
      "description": null,
      "toddler_highlight": null,
      "is_pancake_restaurant": false
    }
  },
  {
    "osm_id": 2911256613,
    "osm_type": "node",
    "name": "Da Wu Sushi & Grill",
    "amenity": "restaurant",
    "lat": 52.4807794,
    "lng": 4.6589338,
    "address": "Meerstraat 90",
    "city": "Beverwijk",
    "website": null,
    "phone": null,
    "cuisine": "sushi;grill",
    "outdoor_seating": null,
    "wheelchair": null,
    "opening_hours": null,
    "scrape": {
      "success": false,
      "error": "no_website",
      "keywords": [],
      "snippet": null
    },
    "evaluation": {
      "score": 4,
      "confidence": "low",
      "reasoning": "Geen website-aanwijzingen gevonden voor kindvriendelijkheid.",
      "has_play_area": null,
      "has_high_chairs": null,
      "has_kids_menu": null,
      "has_diaper_changing": null,
      "weather": null,
      "description": null,
      "toddler_highlight": null,
      "is_pancake_restaurant": false
    }
  },
  {
    "osm_id": 4383715495,
    "osm_type": "node",
    "name": "Cafetaria Family",
    "amenity": "fast_food",
    "lat": 52.4961821,
    "lng": 4.6653995,
    "address": "Büllerlaan 20",
    "city": "Beverwijk",
    "website": null,
    "phone": null,
    "cuisine": null,
    "outdoor_seating": null,
    "wheelchair": "yes",
    "opening_hours": null,
    "scrape": {
      "success": false,
      "error": "no_website",
      "keywords": [],
      "snippet": null
    },
    "evaluation": {
      "score": 4,
      "confidence": "low",
      "reasoning": "Geen website-aanwijzingen gevonden voor kindvriendelijkheid.",
      "has_play_area": null,
      "has_high_chairs": null,
      "has_kids_menu": null,
      "has_diaper_changing": null,
      "weather": null,
      "description": null,
      "toddler_highlight": null,
      "is_pancake_restaurant": false
    }
  },
  {
    "osm_id": 4403276507,
    "osm_type": "node",
    "name": "Lunchroom Ligterink",
    "amenity": "cafe",
    "lat": 52.4818296,
    "lng": 4.6601715,
    "address": "Beverhof 19",
    "city": "Beverwijk",
    "website": null,
    "phone": null,
    "cuisine": null,
    "outdoor_seating": null,
    "wheelchair": null,
    "opening_hours": null,
    "scrape": {
      "success": false,
      "error": "no_website",
      "keywords": [],
      "snippet": null
    },
    "evaluation": {
      "score": 4,
      "confidence": "low",
      "reasoning": "Geen website-aanwijzingen gevonden voor kindvriendelijkheid.",
      "has_play_area": null,
      "has_high_chairs": null,
      "has_kids_menu": null,
      "has_diaper_changing": null,
      "weather": null,
      "description": null,
      "toddler_highlight": null,
      "is_pancake_restaurant": false
    }
  },
  {
    "osm_id": 4403276515,
    "osm_type": "node",
    "name": "I Love Sushi",
    "amenity": "restaurant",
    "lat": 52.4823378,
    "lng": 4.6600444,
    "address": "Beverhof 33",
    "city": "Beverwijk",
    "website": null,
    "phone": null,
    "cuisine": "sushi",
    "outdoor_seating": null,
    "wheelchair": null,
    "opening_hours": null,
    "scrape": {
      "success": false,
      "error": "no_website",
      "keywords": [],
      "snippet": null
    },
    "evaluation": {
      "score": 4,
      "confidence": "low",
      "reasoning": "Geen website-aanwijzingen gevonden voor kindvriendelijkheid.",
      "has_play_area": null,
      "has_high_chairs": null,
      "has_kids_menu": null,
      "has_diaper_changing": null,
      "weather": null,
      "description": null,
      "toddler_highlight": null,
      "is_pancake_restaurant": false
    }
  },
  {
    "osm_id": 4403276518,
    "osm_type": "node",
    "name": "Meat This",
    "amenity": "fast_food",
    "lat": 52.4820426,
    "lng": 4.6603736,
    "address": "Beverhof 35A",
    "city": "Beverwijk",
    "website": null,
    "phone": null,
    "cuisine": null,
    "outdoor_seating": null,
    "wheelchair": null,
    "opening_hours": null,
    "scrape": {
      "success": false,
      "error": "no_website",
      "keywords": [],
      "snippet": null
    },
    "evaluation": {
      "score": 4,
      "confidence": "low",
      "reasoning": "Geen website-aanwijzingen gevonden voor kindvriendelijkheid.",
      "has_play_area": null,
      "has_high_chairs": null,
      "has_kids_menu": null,
      "has_diaper_changing": null,
      "weather": null,
      "description": null,
      "toddler_highlight": null,
      "is_pancake_restaurant": false
    }
  },
  {
    "osm_id": 4451986216,
    "osm_type": "node",
    "name": "Ome Pietje Eten & Drinken",
    "amenity": "restaurant",
    "lat": 52.4835364,
    "lng": 4.6553049,
    "address": "Baanstraat 53c",
    "city": "Beverwijk",
    "website": null,
    "phone": null,
    "cuisine": null,
    "outdoor_seating": null,
    "wheelchair": null,
    "opening_hours": null,
    "scrape": {
      "success": false,
      "error": "no_website",
      "keywords": [],
      "snippet": null
    },
    "evaluation": {
      "score": 4,
      "confidence": "low",
      "reasoning": "Geen website-aanwijzingen gevonden voor kindvriendelijkheid.",
      "has_play_area": null,
      "has_high_chairs": null,
      "has_kids_menu": null,
      "has_diaper_changing": null,
      "weather": null,
      "description": null,
      "toddler_highlight": null,
      "is_pancake_restaurant": false
    }
  },
  {
    "osm_id": 5169019279,
    "osm_type": "node",
    "name": "Brafoer",
    "amenity": "restaurant",
    "lat": 52.4788219,
    "lng": 4.6538731,
    "address": "Halve Maan 2",
    "city": "Beverwijk",
    "website": null,
    "phone": null,
    "cuisine": null,
    "outdoor_seating": null,
    "wheelchair": "yes",
    "opening_hours": "Mo-Su 09:30-21:30+",
    "scrape": {
      "success": false,
      "error": "no_website",
      "keywords": [],
      "snippet": null
    },
    "evaluation": {
      "score": 4,
      "confidence": "low",
      "reasoning": "Geen website-aanwijzingen gevonden voor kindvriendelijkheid.",
      "has_play_area": null,
      "has_high_chairs": null,
      "has_kids_menu": null,
      "has_diaper_changing": null,
      "weather": null,
      "description": null,
      "toddler_highlight": null,
      "is_pancake_restaurant": false
    }
  },
  {
    "osm_id": 6126829975,
    "osm_type": "node",
    "name": "Gasterij Vuurland",
    "amenity": "restaurant",
    "lat": 52.4760157,
    "lng": 4.6816905,
    "address": "Noorderweg 15",
    "city": "Beverwijk",
    "website": null,
    "phone": null,
    "cuisine": null,
    "outdoor_seating": null,
    "wheelchair": null,
    "opening_hours": null,
    "scrape": {
      "success": false,
      "error": "no_website",
      "keywords": [],
      "snippet": null
    },
    "evaluation": {
      "score": 4,
      "confidence": "low",
      "reasoning": "Geen website-aanwijzingen gevonden voor kindvriendelijkheid.",
      "has_play_area": null,
      "has_high_chairs": null,
      "has_kids_menu": null,
      "has_diaper_changing": null,
      "weather": null,
      "description": null,
      "toddler_highlight": null,
      "is_pancake_restaurant": false
    }
  },
  {
    "osm_id": 6225066961,
    "osm_type": "node",
    "name": "Dirk's Vis En Meer",
    "amenity": "fast_food",
    "lat": 52.4780824,
    "lng": 4.6597892,
    "address": null,
    "city": null,
    "website": null,
    "phone": "+31 6 28313644",
    "cuisine": "fish;seafood;fish_and_chips;meat",
    "outdoor_seating": "yes",
    "wheelchair": null,
    "opening_hours": "Mo-Su 11:00-19:00",
    "scrape": {
      "success": false,
      "error": "no_website",
      "keywords": [],
      "snippet": null
    },
    "evaluation": {
      "score": 4,
      "confidence": "low",
      "reasoning": "Geen website-aanwijzingen gevonden voor kindvriendelijkheid.",
      "has_play_area": null,
      "has_high_chairs": null,
      "has_kids_menu": null,
      "has_diaper_changing": null,
      "weather": null,
      "description": null,
      "toddler_highlight": null,
      "is_pancake_restaurant": false
    }
  },
  {
    "osm_id": 6698491998,
    "osm_type": "node",
    "name": "Oost 3",
    "amenity": "restaurant",
    "lat": 52.4981236,
    "lng": 4.5872292,
    "address": "Relweg",
    "city": "Wijk aan Zee",
    "website": null,
    "phone": null,
    "cuisine": "regional",
    "outdoor_seating": "yes",
    "wheelchair": "yes",
    "opening_hours": null,
    "scrape": {
      "success": false,
      "error": "no_website",
      "keywords": [],
      "snippet": null
    },
    "evaluation": {
      "score": 4,
      "confidence": "low",
      "reasoning": "Geen website-aanwijzingen gevonden voor kindvriendelijkheid.",
      "has_play_area": null,
      "has_high_chairs": null,
      "has_kids_menu": null,
      "has_diaper_changing": null,
      "weather": null,
      "description": null,
      "toddler_highlight": null,
      "is_pancake_restaurant": false
    }
  },
  {
    "osm_id": 7154699541,
    "osm_type": "node",
    "name": "Burger King",
    "amenity": "fast_food",
    "lat": 52.4751233,
    "lng": 4.6570598,
    "address": "Parallelweg 1B",
    "city": "Beverwijk",
    "website": null,
    "phone": null,
    "cuisine": "burger",
    "outdoor_seating": null,
    "wheelchair": null,
    "opening_hours": null,
    "scrape": {
      "success": false,
      "error": "no_website",
      "keywords": [],
      "snippet": null
    },
    "evaluation": {
      "score": 4,
      "confidence": "low",
      "reasoning": "Geen website-aanwijzingen gevonden voor kindvriendelijkheid.",
      "has_play_area": null,
      "has_high_chairs": null,
      "has_kids_menu": null,
      "has_diaper_changing": null,
      "weather": null,
      "description": null,
      "toddler_highlight": null,
      "is_pancake_restaurant": false
    }
  },
  {
    "osm_id": 7154699548,
    "osm_type": "node",
    "name": "KFC",
    "amenity": "fast_food",
    "lat": 52.4752938,
    "lng": 4.6571525,
    "address": "Parallelweg 1A",
    "city": "Beverwijk",
    "website": null,
    "phone": "+31 251 744 038",
    "cuisine": "chicken",
    "outdoor_seating": null,
    "wheelchair": null,
    "opening_hours": null,
    "scrape": {
      "success": false,
      "error": "no_website",
      "keywords": [],
      "snippet": null
    },
    "evaluation": {
      "score": 4,
      "confidence": "low",
      "reasoning": "Geen website-aanwijzingen gevonden voor kindvriendelijkheid.",
      "has_play_area": null,
      "has_high_chairs": null,
      "has_kids_menu": null,
      "has_diaper_changing": null,
      "weather": null,
      "description": null,
      "toddler_highlight": null,
      "is_pancake_restaurant": false
    }
  },
  {
    "osm_id": 10221628243,
    "osm_type": "node",
    "name": "Wegrestaurant Zacht Staal",
    "amenity": "restaurant",
    "lat": 52.4737471,
    "lng": 4.6945534,
    "address": "Noorderweg 991",
    "city": "Beverwijk",
    "website": null,
    "phone": null,
    "cuisine": null,
    "outdoor_seating": null,
    "wheelchair": null,
    "opening_hours": null,
    "scrape": {
      "success": false,
      "error": "no_website",
      "keywords": [],
      "snippet": null
    },
    "evaluation": {
      "score": 4,
      "confidence": "low",
      "reasoning": "Geen website-aanwijzingen gevonden voor kindvriendelijkheid.",
      "has_play_area": null,
      "has_high_chairs": null,
      "has_kids_menu": null,
      "has_diaper_changing": null,
      "weather": null,
      "description": null,
      "toddler_highlight": null,
      "is_pancake_restaurant": false
    }
  },
  {
    "osm_id": 10783600763,
    "osm_type": "node",
    "name": "Podiumcafé TOOS",
    "amenity": "cafe",
    "lat": 52.4766284,
    "lng": 4.6582404,
    "address": null,
    "city": null,
    "website": null,
    "phone": null,
    "cuisine": "bistro",
    "outdoor_seating": null,
    "wheelchair": null,
    "opening_hours": "We-Su 12:00-22:00",
    "scrape": {
      "success": false,
      "error": "no_website",
      "keywords": [],
      "snippet": null
    },
    "evaluation": {
      "score": 4,
      "confidence": "low",
      "reasoning": "Geen website-aanwijzingen gevonden voor kindvriendelijkheid.",
      "has_play_area": null,
      "has_high_chairs": null,
      "has_kids_menu": null,
      "has_diaper_changing": null,
      "weather": null,
      "description": null,
      "toddler_highlight": null,
      "is_pancake_restaurant": false
    }
  }
]